unblockr/__init__.py
unblockr/chrome.py
unblockr/firefox.py
unblockr-2.1.2.dist-info/LICENSE.txt
unblockr-2.1.2.dist-info/METADATA
unblockr-2.1.2.dist-info/WHEEL
unblockr-2.1.2.dist-info/top_level.txt
unblockr-2.1.2.dist-info/RECORD
