Metadata-Version: 2.1
Name: unblockr
Version: 2.1.2
Summary: A python package used for creating alternate browsers
Home-page: UNKNOWN
Author: Bob Brown
License: UNKNOWN
Platform: UNKNOWN
Classifier: Programming Language :: Python :: 3
Classifier: License :: OSI Approved :: MIT License
Classifier: Operating System :: OS Independent
Requires-Python: >=3.6
License-File: LICENSE.txt
Requires-Dist: selenium
Requires-Dist: webbot
